Workbook

Sheet Plan1
B2: STATUS GERAL
B3: PEDIDO | C3: VENDEDOR | D3: CODIGO | E3: DATA | F3: DIVERGENCIA | G3: CLIENTE
B4: 195474 | C4: MARTA | D4: 67493 | E4: 46129 | F4: ZERAR ESTOQUE | G4: =_xlfn.XLOOKUP(Tabela1[[#This Row],[PEDIDO]],'BASE_5 2 3 B'!AB:AB,'BASE_5 2 3 B'!I:I) -> METALMUNDI IND.COM.SER.LTDA
B5: 195485 | C5: ANA | D5: 58078 | E5: 46129 | F5: FISICO 81 | G5: =_xlfn.XLOOKUP(Tabela1[[#This Row],[PEDIDO]],'BASE_5 2 3 B'!AB:AB,'BASE_5 2 3 B'!I:I) -> #N/A
B6: 195497 | C6: ANA | D6: 4422 | E6: 46132 | F6: ZERAR ESTOQUE | G6: =_xlfn.XLOOKUP(Tabela1[[#This Row],[PEDIDO]],'BASE_5 2 3 B'!AB:AB,'BASE_5 2 3 B'!I:I) -> MINERACAO VERA CRUZ LTDA
B7: 195457 | C7: ANA | D7: 47656 | E7: 46132 | F7: ZERAR ESTOQUE | G7: =_xlfn.XLOOKUP(Tabela1[[#This Row],[PEDIDO]],'BASE_5 2 3 B'!AB:AB,'BASE_5 2 3 B'!I:I) -> NAT CEREAIS E ALIMENTOS LTDA.
B8: 195520 | C8: JOSÉ | D8: 48579 | E8: 46132 | F8: ZERAR ESTOQUE | G8: =_xlfn.XLOOKUP(Tabela1[[#This Row],[PEDIDO]],'BASE_5 2 3 B'!AB:AB,'BASE_5 2 3 B'!I:I) -> MADEIREIRA GIGANTE LTDA
B9: 195566 | C9: ANA | D9: 56862 | E9: 46134 | F9: fisico 223 | G9: =_xlfn.XLOOKUP(Tabela1[[#This Row],[PEDIDO]],'BASE_5 2 3 B'!AB:AB,'BASE_5 2 3 B'!I:I) -> #N/A
B10: 195625 | C10: WILIAM | D10: 51697 | E10: 46134 | F10: ZERAR ESTOQUE | G10: =_xlfn.XLOOKUP(Tabela1[[#This Row],[PEDIDO]],'BASE_5 2 3 B'!AB:AB,'BASE_5 2 3 B'!I:I) -> #N/A
B11: 195714 | C11: RENAN | D11: 65377 | E11: 46134 | F11: ZERAR ESTOQUE | G11: =_xlfn.XLOOKUP(Tabela1[[#This Row],[PEDIDO]],'BASE_5 2 3 B'!AB:AB,'BASE_5 2 3 B'!I:I) -> #N/A
B12: 195720 | C12: ANA | D12: 5633 | E12: 46135 | F12: ZERAR ESTOQUE | G12: =_xlfn.XLOOKUP(Tabela1[[#This Row],[PEDIDO]],'BASE_5 2 3 B'!AB:AB,'BASE_5 2 3 B'!I:I) -> #N/A
B13: 195784 | C13: ANA | D13: 68683 | E13: 46135 | F13: ZERAR ESTOQUE | G13: =_xlfn.XLOOKUP(Tabela1[[#This Row],[PEDIDO]],'BASE_5 2 3 B'!AB:AB,'BASE_5 2 3 B'!I:I) -> #N/A
B14: 195687 | C14: PATRICIA | D14: 54537 | E14: 46135 | F14: ZERAR ESTOQUE | G14: =_xlfn.XLOOKUP(Tabela1[[#This Row],[PEDIDO]],'BASE_5 2 3 B'!AB:AB,'BASE_5 2 3 B'!I:I) -> #N/A
B15: 195815 | C15: ANA | D15: 47874 | E15: 46135 | F15: ZERAR ESTOQUE | G15: =_xlfn.XLOOKUP(Tabela1[[#This Row],[PEDIDO]],'BASE_5 2 3 B'!AB:AB,'BASE_5 2 3 B'!I:I) -> #N/A
... B32: 193122 | C32: TIAGO | D32: 50644 | E32: 46139 | F32: ZERAR ESTOQUE | G32: =_xlfn.XLOOKUP(Tabela1[[#This Row],[PEDIDO]],'BASE_5 2 3 B'!AB:AB,'BASE_5 2 3 B'!I:I) -> SCS IND.COM.DE EMBARCACOES LTD

Sheet BASE_5 2 3 B
A1: Nome da Origem | B1: Column1 | C1: Série | D1: Nota | E1: Posição detalhada | F1: CFOP | G1: CFOP_1 | H1: Cli/for | I1: Razão social | J1: Cidade | K1: UF | L1: Dt.fatur | M1: Vlr.nota | N1: Fatura | O1: ID nota | P1: Situação da NF-e | Q1: Pedido | R1: Cubagem volumes | S1: Peso bruto volume | T1: Qtd.volume | U1: Via tran | V1: Abreviação | W1: Código | X1: Peso líq.volume | Y1: Obs.comerc | Z1: Desc.repr/prep | AA1: Column26 | AB1: PEDIDO NUMERO
A2: SIGER_XLS_944116_260326_100411.xlsx | E2: P/faturar | F2: 5405 | H2: 100 | I2: VENDAS A CONSUMIDOR | J2: PORTO ALEGRE | K2: RS-Rio Grande do Sul | L2: 46028 | M2: 54.15 | O2: 242135 | Q2: Cód: 0 | U2: 1-Rodoviário | V2: DESTINATÁRIO | W2: 2 | Z2: RAEL | AB2: =VALUE(SUBSTITUTE(BASE_5_2_3_B[[#This Row],[Pedido]],"Cód: ","")) -> 0
A3: SIGER_XLS_944116_260326_100411.xlsx | E3: P/faturar | F3: 5405 | H3: 100 | I3: VENDAS A CONSUMIDOR | J3: PORTO ALEGRE | K3: RS-Rio Grande do Sul | L3: 46030 | M3: 5.1 | O3: 242503 | Q3: Cód: 0 | U3: 1-Rodoviário | V3: DESTINATÁRIO | W3: 2 | Z3: RAEL | AB3: =VALUE(SUBSTITUTE(BASE_5_2_3_B[[#This Row],[Pedido]],"Cód: ","")) -> 0
A4: SIGER_XLS_944116_260326_100411.xlsx | E4: Cancelada | F4: 5405 | H4: 100 | I4: VENDAS A CONSUMIDOR | J4: PORTO ALEGRE | K4: RS-Rio Grande do Sul | L4: 46031 | M4: 40.63 | O4: 242630 | Q4: Cód: 0 | U4: 1-Rodoviário | Z4: ALEX | AB4: =VALUE(SUBSTITUTE(BASE_5_2_3_B[[#This Row],[Pedido]],"Cód: ","")) -> 0
A5: SIGER_XLS_944116_260326_100411.xlsx | E5: Cancelada | F5: 5405 | H5: 100 | I5: VENDAS A CONSUMIDOR | J5: PORTO ALEGRE | K5: RS-Rio Grande do Sul | L5: 46031 | M5: 40.63 | O5: 242631 | Q5: Cód: 0 | U5: 1-Rodoviário | Z5: ALEX | AB5: =VALUE(SUBSTITUTE(BASE_5_2_3_B[[#This Row],[Pedido]],"Cód: ","")) -> 0
A6: SIGER_XLS_944116_260326_100411.xlsx | E6: Cancelada | F6: 6108 | H6: 15719 | I6: KMV ENGENHAR.DE EQUIP.INDS.LTD | J6: DIADEMA | K6: SP-São Paulo | L6: 46031 | M6: 1471.82 | O6: 242692 | P6: NF-e rejeitada | Q6: Cód: 184955 | T6: 2 | U6: 1-Rodoviário | V6: DESTINATÁRIO | W6: 2 | Y6: JENNIFER | Z6: ANA | AB6: =VALUE(SUBSTITUTE(BASE_5_2_3_B[[#This Row],[Pedido]],"Cód: ","")) -> 184955
A7: SIGER_XLS_944116_260326_100411.xlsx | E7: Cancelada | F7: 6108 | H7: 15724 | I7: JB NOROESTE TRANSPORTES LTDA. | J7: BAURU | K7: SP-São Paulo | L7: 46034 | M7: 527.65 | O7: 242791 | P7: NF-e rejeitada | Q7: Cód: 185109 | T7: 1 | U7: 1-Rodoviário | V7: RÉGIS | W7: 4 | Y7: ALISSON | Z7: ANA | AB7: =VALUE(SUBSTITUTE(BASE_5_2_3_B[[#This Row],[Pedido]],"Cód: ","")) -> 185109
A8: SIGER_XLS_944116_260326_100411.xlsx | E8: Cancelada | F8: 1411 | H8: 15741 | I8: FERNANDO DA SILVA PINTO | J8: PORTO ALEGRE | K8: RS-Rio Grande do Sul | L8: 46035 | M8: 149.29 | O8: 242997 | P8: NF-e rejeitada | Q8: Cód: 0 | U8: 1-Rodoviário | V8: EMITENTE | W8: 1 | AB8: =VALUE(SUBSTITUTE(BASE_5_2_3_B[[#This Row],[Pedido]],"Cód: ","")) -> 0
A9: SIGER_XLS_944116_260326_100411.xlsx | E9: Cancelada | F9: 1411 | H9: 15741 | I9: FERNANDO DA SILVA PINTO | J9: PORTO ALEGRE | K9: RS-Rio Grande do Sul | L9: 46035 | M9: 149.29 | O9: 243000 | P9: NF-e rejeitada | Q9: Cód: 0 | U9: 1-Rodoviário | V9: EMITENTE | W9: 1 | AB9: =VALUE(SUBSTITUTE(BASE_5_2_3_B[[#This Row],[Pedido]],"Cód: ","")) -> 0
A10: SIGER_XLS_944116_260326_100411.xlsx | E10: P/faturar | F10: 5405 | H10: 100 | I10: VENDAS A CONSUMIDOR | J10: PORTO ALEGRE | K10: RS-Rio Grande do Sul | L10: 46036 | M10: 849.2 | O10: 243173 | Q10: Cód: 0 | U10: 1-Rodoviário | V10: DESTINATÁRIO | W10: 2 | Z10: RAEL | AB10: =VALUE(SUBSTITUTE(BASE_5_2_3_B[[#This Row],[Pedido]],"Cód: ","")) -> 0
A11: SIGER_XLS_944116_260326_100411.xlsx | E11: Cancelada | F11: 5405 | H11: 100 | I11: VENDAS A CONSUMIDOR | J11: PORTO ALEGRE | K11: RS-Rio Grande do Sul | L11: 46037 | M11: 18.38 | O11: 243341 | Q11: Cód: 0 | U11: 1-Rodoviário | Z11: PATRICIA | AB11: =VALUE(SUBSTITUTE(BASE_5_2_3_B[[#This Row],[Pedido]],"Cód: ","")) -> 0
A12: SIGER_XLS_944116_260326_100411.xlsx | E12: P/faturar | F12: 5405 | H12: 100 | I12: VENDAS A CONSUMIDOR | J12: PORTO ALEGRE | K12: RS-Rio Grande do Sul | L12: 46038 | M12: 519.16 | O12: 243492 | Q12: Cód: 0 | U12: 1-Rodoviário | V12: DESTINATÁRIO | W12: 2 | Z12: RAEL | AB12: =VALUE(SUBSTITUTE(BASE_5_2_3_B[[#This Row],[Pedido]],"Cód: ","")) -> 0
A13: SIGER_XLS_944116_260326_100411.xlsx | E13: P/faturar (Separada) | F13: 5405 | H13: 6093 | I13: LAZZARI IND.COM.MOBILIARIO URBAN | J13: PORTO ALEGRE | K13: RS-Rio Grande do Sul | L13: 46042 | M13: 24.56 | O13: 243945 | Q13: Cód: 186224 | T13: 1 | U13: 1-Rodoviário | V13: DESTINATÁRIO | W13: 2 | Y13: DANIIIIIIIIIIIIIIIIII | Z13: MARTA | AB13: =VALUE(SUBSTITUTE(BASE_5_2_3_B[[#This Row],[Pedido]],"Cód: ","")) -> 186224
A14: SIGER_XLS_944116_260326_100411.xlsx | E14: Cancelada | F14: 6108 | H14: 15792 | I14: VISTA SEMPRE ALEM LTDA | J14: SAO PAULO | K14: SP-São Paulo | L14: 46048 | M14: 75.9 | O14: 244527 | P14: NF-e rejeitada | Q14: Cód: 186754 | U14: 1-Rodoviário | V14: DESTINATÁRIO | W14: 2 | Z14: RAEL | AB14: =VALUE(SUBSTITUTE(BASE_5_2_3_B[[#This Row],[Pedido]],"Cód: ","")) -> 186754
A15: SIGER_XLS_944116_260326_100411.xlsx | E15: P/faturar (Separada) | F15: 5405 | H15: 7682 | I15: FÁB.DE EMBUTIDOS BORRUSSIA LTDA | J15: OSORIO | K15: RS-Rio Grande do Sul | L15: 46049 | M15: 40.92 | O15: 249368 | Q15: Cód: 186887 | T15: 1 | U15: 1-Rodoviário | V15: SAO MIGUEL | W15: 6 | Y15: EVERTON | Z15: ANA | AB15: =VALUE(SUBSTITUTE(BASE_5_2_3_B[[#This Row],[Pedido]],"Cód: ","")) -> 186887
A16: SIGER_XLS_944116_260326_100411.xlsx | C16: 8 | D16: 93 | E16: Faturada | F16: 5405 | H16: 100 | I16: VENDAS A CONSUMIDOR | J16: PORTO ALEGRE | K16: RS-Rio Grande do Sul | L16: 46028 | M16: 34.72 | O16: 242024 | P16: NFC-e enviada | Q16: Cód: 0 | U16: 1-Rodoviário | Z16: PATRICIA | AB16: =VALUE(SUBSTITUTE(BASE_5_2_3_B[[#This Row],[Pedido]],"Cód: ","")) -> 0
A17: SIGER_XLS_944116_260326_100411.xlsx | C17: 8 | D17: 94 | E17: Faturada | F17: 5405 | H17: 100 | I17: VENDAS A CONSUMIDOR | J17: PORTO ALEGRE | K17: RS-Rio Grande do Sul | L17: 46028 | M17: 75.52 | O17: 242025 | P17: NFC-e enviada | Q17: Cód: 0 | U17: 1-Rodoviário | Z17: PATRICIA | AB17: =VALUE(SUBSTITUTE(BASE_5_2_3_B[[#This Row],[Pedido]],"Cód: ","")) -> 0
A18: SIGER_XLS_944116_260326_100411.xlsx | C18: 8 | D18: 95 | E18: Faturada | F18: 5405 | H18: 100 | I18: VENDAS A CONSUMIDOR | J18: PORTO ALEGRE | K18: RS-Rio Grande do Sul | L18: 46028 | M18: 9.14 | O18: 242054 | P18: NFC-e enviada | Q18: Cód: 0 | U18: 1-Rodoviário | Z18: PATRICIA | AB18: =VALUE(SUBSTITUTE(BASE_5_2_3_B[[#This Row],[Pedido]],"Cód: ","")) -> 0
A19: SIGER_XLS_944116_260326_100411.xlsx | C19: 8 | D19: 96 | E19: Faturada | F19: 5102 | G19: 5405 | H19: 100 | I19: VENDAS A CONSUMIDOR | J19: PORTO ALEGRE | K19: RS-Rio Grande do Sul | L19: 46028 | M19: 10.87 | O19: 242057 | P19: NFC-e enviada | Q19: Cód: 0 | U19: 1-Rodoviário | Z19: PATRICIA | AB19: =VALUE(SUBSTITUTE(BASE_5_2_3_B[[#This Row],[Pedido]],"Cód: ","")) -> 0
A20: SIGER_XLS_944116_260326_100411.xlsx | C20: 8 | D20: 97 | E20: Faturada | F20: 5405 | H20: 100 | I20: VENDAS A CONSUMIDOR | J20: PORTO ALEGRE | K20: RS-Rio Grande do Sul | L20: 46028 | M20: 6.95 | O20: 242064 | P20: NFC-e enviada | Q20: Cód: 0 | U20: 1-Rodoviário | Z20: PATRICIA | AB20: =VALUE(SUBSTITUTE(BASE_5_2_3_B[[#This Row],[Pedido]],"Cód: ","")) -> 0
A21: SIGER_XLS_944116_260326_100411.xlsx | C21: 8 | D21: 98 | E21: Faturada | F21: 5405 | H21: 100 | I21: VENDAS A CONSUMIDOR | J21: PORTO ALEGRE | K21: RS-Rio Grande do Sul | L21: 46028 | M21: 14.78 | O21: 242067 | P21: NFC-e enviada | Q21: Cód: 0 | U21: 1-Rodoviário | Z21: PATRICIA | AB21: =VALUE(SUBSTITUTE(BASE_5_2_3_B[[#This Row],[Pedido]],"Cód: ","")) -> 0
A22: SIGER_XLS_944116_260326_100411.xlsx | C22: 8 | D22: 99 | E22: Faturada | F22: 5405 | H22: 100 | I22: VENDAS A CONSUMIDOR | J22: PORTO ALEGRE | K22: RS-Rio Grande do Sul | L22: 46028 | M22: 33.88 | O22: 242076 | P22: NFC-e enviada | Q22: Cód: 0 | U22: 1-Rodoviário | Z22: PATRICIA | AB22: =VALUE(SUBSTITUTE(BASE_5_2_3_B[[#This Row],[Pedido]],"Cód: ","")) -> 0
A23: SIGER_XLS_944116_260326_100411.xlsx | C23: 8 | D23: 100 | E23: Faturada | F23: 5405 | H23: 100 | I23: VENDAS A CONSUMIDOR | J23: PORTO ALEGRE | K23: RS-Rio Grande do Sul | L23: 46028 | M23: 88.41 | O23: 242079 | P23: NFC-e enviada | Q23: Cód: 0 | U23: 1-Rodoviário | Z23: RAEL | AB23: =VALUE(SUBSTITUTE(BASE_5_2_3_B[[#This Row],[Pedido]],"Cód: ","")) -> 0
A24: SIGER_XLS_944116_260326_100411.xlsx | C24: 8 | D24: 101 | E24: Faturada | F24: 5405 | H24: 100 | I24: VENDAS A CONSUMIDOR | J24: PORTO ALEGRE | K24: RS-Rio Grande do Sul | L24: 46028 | M24: 37.4 | O24: 242083 | P24: NFC-e enviada | Q24: Cód: 0 | U24: 1-Rodoviário | Z24: PATRICIA | AB24: =VALUE(SUBSTITUTE(BASE_5_2_3_B[[#This Row],[Pedido]],"Cód: ","")) -> 0
A25: SIGER_XLS_944116_260326_100411.xlsx | C25: 8 | D25: 102 | E25: Faturada | F25: 5405 | H25: 100 | I25: VENDAS A CONSUMIDOR | J25: PORTO ALEGRE | K25: RS-Rio Grande do Sul | L25: 46028 | M25: 57.66 | O25: 242089 | P25: NFC-e enviada | Q25: Cód: 0 | U25: 1-Rodoviário | Z25: PATRICIA | AB25: =VALUE(SUBSTITUTE(BASE_5_2_3_B[[#This Row],[Pedido]],"Cód: ","")) -> 0
A26: SIGER_XLS_944116_260326_100411.xlsx | C26: 8 | D26: 103 | E26: Faturada | F26: 5102 | H26: 11771 | I26: PAULO KAWAN | J26: PORTO ALEGRE | K26: RS-Rio Grande do Sul | L26: 46028 | M26: 29.03 | O26: 242093 | P26: NFC-e enviada | Q26: Cód: 0 | U26: 1-Rodoviário | Z26: PATRICIA | AB26: =VALUE(SUBSTITUTE(BASE_5_2_3_B[[#This Row],[Pedido]],"Cód: ","")) -> 0
A27: SIGER_XLS_944116_260326_100411.xlsx | C27: 8 | D27: 104 | E27: Faturada | F27: 5102 | H27: 100 | I27: VENDAS A CONSUMIDOR | J27: PORTO ALEGRE | K27: RS-Rio Grande do Sul | L27: 46028 | M27: 127.3 | O27: 242121 | P27: NFC-e enviada | Q27: Cód: 0 | U27: 1-Rodoviário | Z27: PATRICIA | AB27: =VALUE(SUBSTITUTE(BASE_5_2_3_B[[#This Row],[Pedido]],"Cód: ","")) -> 0
A28: SIGER_XLS_944116_260326_100411.xlsx | C28: 8 | D28: 105 | E28: Faturada | F28: 5405 | H28: 100 | I28: VENDAS A CONSUMIDOR | J28: PORTO ALEGRE | K28: RS-Rio Grande do Sul | L28: 46028 | M28: 5.01 | O28: 242138 | P28: NFC-e enviada | Q28: Cód: 0 | U28: 1-Rodoviário | Z28: PATRICIA | AB28: =VALUE(SUBSTITUTE(BASE_5_2_3_B[[#This Row],[Pedido]],"Cód: ","")) -> 0
A29: SIGER_XLS_944116_260326_100411.xlsx | C29: 8 | D29: 106 | E29: Faturada | F29: 5405 | H29: 100 | I29: VENDAS A CONSUMIDOR | J29: PORTO ALEGRE | K29: RS-Rio Grande do Sul | L29: 46028 | M29: 29.48 | O29: 242161 | P29: NFC-e enviada | Q29: Cód: 0 | U29: 1-Rodoviário | Z29: PATRICIA | AB29: =VALUE(SUBSTITUTE(BASE_5_2_3_B[[#This Row],[Pedido]],"Cód: ","")) -> 0
A30: SIGER_XLS_944116_260326_100411.xlsx | C30: 8 | D30: 107 | E30: Faturada | F30: 5102 | G30: 5405 | H30: 100 | I30: VENDAS A CONSUMIDOR | J30: PORTO ALEGRE | K30: RS-Rio Grande do Sul | L30: 46028 | M30: 279.89 | O30: 242163 | P30: NFC-e enviada | Q30: Cód: 0 | U30: 1-Rodoviário | Z30: PATRICIA | AB30: =VALUE(SUBSTITUTE(BASE_5_2_3_B[[#This Row],[Pedido]],"Cód: ","")) -> 0
A31: SIGER_XLS_944116_260326_100411.xlsx | C31: 8 | D31: 108 | E31: Faturada | F31: 5405 | H31: 100 | I31: VENDAS A CONSUMIDOR | J31: PORTO ALEGRE | K31: RS-Rio Grande do Sul | L31: 46028 | M31: 46.46 | O31: 242171 | P31: NFC-e enviada | Q31: Cód: 0 | U31: 1-Rodoviário | Z31: PATRICIA | AB31: =VALUE(SUBSTITUTE(BASE_5_2_3_B[[#This Row],[Pedido]],"Cód: ","")) -> 0
A32: SIGER_XLS_944116_260326_100411.xlsx | C32: 8 | D32: 109 | E32: Cancelada | F32: 5405 | H32: 100 | I32: VENDAS A CONSUMIDOR | J32: PORTO ALEGRE | K32: RS-Rio Grande do Sul | L32: 46028 | M32: 5 | O32: 242175 | P32: NFC-e cancelada | Q32: Cód: 0 | U32: 1-Rodoviário | Z32: PATRICIA | AB32: =VALUE(SUBSTITUTE(BASE_5_2_3_B[[#This Row],[Pedido]],"Cód: ","")) -> 0
A33: SIGER_XLS_944116_260326_100411.xlsx | C33: 8 | D33: 110 | E33: Faturada | F33: 5405 | H33: 100 | I33: VENDAS A CONSUMIDOR | J33: PORTO ALEGRE | K33: RS-Rio Grande do Sul | L33: 46028 | M33: 5 | O33: 242176 | P33: NFC-e enviada | Q33: Cód: 0 | U33: 1-Rodoviário | Z33: PATRICIA | AB33: =VALUE(SUBSTITUTE(BASE_5_2_3_B[[#This Row],[Pedido]],"Cód: ","")) -> 0
A34: SIGER_XLS_944116_260326_100411.xlsx | C34: 8 | D34: 111 | E34: Faturada | F34: 5405 | H34: 100 | I34: VENDAS A CONSUMIDOR | J34: PORTO ALEGRE | K34: RS-Rio Grande do Sul | L34: 46028 | M34: 5.77 | O34: 242189 | P34: NFC-e enviada | Q34: Cód: 0 | U34: 1-Rodoviário | Z34: PATRICIA | AB34: =VALUE(SUBSTITUTE(BASE_5_2_3_B[[#This Row],[Pedido]],"Cód: ","")) -> 0
A35: SIGER_XLS_944116_260326_100411.xlsx | C35: 8 | D35: 112 | E35: Faturada | F35: 5405 | H35: 100 | I35: VENDAS A CONSUMIDOR | J35: PORTO ALEGRE | K35: RS-Rio Grande do Sul | L35: 46029 | M35: 243.08 | O35: 242210 | P35: NFC-e enviada | Q35: Cód: 0 | U35: 1-Rodoviário | Z35: PATRICIA | AB35: =VALUE(SUBSTITUTE(BASE_5_2_3_B[[#This Row],[Pedido]],"Cód: ","")) -> 0
A36: SIGER_XLS_944116_260326_100411.xlsx | C36: 8 | D36: 113 | E36: Faturada | F36: 5102 | G36: 5405 | H36: 100 | I36: VENDAS A CONSUMIDOR | J36: PORTO ALEGRE | K36: RS-Rio Grande do Sul | L36: 46029 | M36: 36.66 | O36: 242219 | P36: NFC-e enviada | Q36: Cód: 0 | U36: 1-Rodoviário | Z36: PATRICIA | AB36: =VALUE(SUBSTITUTE(BASE_5_2_3_B[[#This Row],[Pedido]],"Cód: ","")) -> 0
A37: SIGER_XLS_944116_260326_100411.xlsx | C37: 8 | D37: 114 | E37: Faturada | F37: 5405 | H37: 100 | I37: VENDAS A CONSUMIDOR | J37: PORTO ALEGRE | K37: RS-Rio Grande do Sul | L37: 46029 | M37: 5.16 | O37: 242223 | P37: NFC-e enviada | Q37: Cód: 0 | U37: 1-Rodoviário | Z37: PATRICIA | AB37: =VALUE(SUBSTITUTE(BASE_5_2_3_B[[#This Row],[Pedido]],"Cód: ","")) -> 0
A38: SIGER_XLS_944116_260326_100411.xlsx | C38: 8 | D38: 115 | E38: Faturada | F38: 5102 | G38: 5405 | H38: 100 | I38: VENDAS A CONSUMIDOR | J38: PORTO ALEGRE | K38: RS-Rio Grande do Sul | L38: 46029 | M38: 60.62 | O38: 242237 | P38: NFC-e enviada | Q38: Cód: 0 | U38: 1-Rodoviário | Z38: PATRICIA | AB38: =VALUE(SUBSTITUTE(BASE_5_2_3_B[[#This Row],[Pedido]],"Cód: ","")) -> 0
A39: SIGER_XLS_944116_260326_100411.xlsx | C39: 8 | D39: 116 | E39: Faturada | F39: 5405 | H39: 100 | I39: VENDAS A CONSUMIDOR | J39: PORTO ALEGRE | K39: RS-Rio Grande do Sul | L39: 46029 | M39: 5 | O39: 242241 | P39: NFC-e enviada | Q39: Cód: 0 | U39: 1-Rodoviário | Z39: PATRICIA | AB39: =VALUE(SUBSTITUTE(BASE_5_2_3_B[[#This Row],[Pedido]],"Cód: ","")) -> 0
A40: SIGER_XLS_944116_260326_100411.xlsx | C40: 8 | D40: 117 | E40: Faturada | F40: 5102 | G40: 5405 | H40: 100 | I40: VENDAS A CONSUMIDOR | J40: PORTO ALEGRE | K40: RS-Rio Grande do Sul | L40: 46029 | M40: 82.97 | O40: 242242 | P40: NFC-e enviada | Q40: Cód: 0 | U40: 1-Rodoviário | Z40: PATRICIA | AB40: =VALUE(SUBSTITUTE(BASE_5_2_3_B[[#This Row],[Pedido]],"Cód: ","")) -> 0
A41: SIGER_XLS_944116_260326_100411.xlsx | C41: 8 | D41: 118 | E41: Faturada | F41: 5405 | H41: 100 | I41: VENDAS A CONSUMIDOR | J41: PORTO ALEGRE | K41: RS-Rio Grande do Sul | L41: 46029 | M41: 95.22 | O41: 242253 | P41: NFC-e enviada | Q41: Cód: 0 | U41: 1-Rodoviário | Z41: PATRICIA | AB41: =VALUE(SUBSTITUTE(BASE_5_2_3_B[[#This Row],[Pedido]],"Cód: ","")) -> 0
A42: SIGER_XLS_944116_260326_100411.xlsx | C42: 8 | D42: 119 | E42: Faturada | F42: 5405 | H42: 14171 | I42: ANGELO RICARDO MARRONE | J42: PORTO ALEGRE | K42: RS-Rio Grande do Sul | L42: 46029 | M42: 11.57 | O42: 242265 | P42: NFC-e enviada | Q42: Cód: 0 | U42: 1-Rodoviário | Z42: PATRICIA | AB42: =VALUE(SUBSTITUTE(BASE_5_2_3_B[[#This Row],[Pedido]],"Cód: ","")) -> 0
A43: SIGER_XLS_944116_260326_100411.xlsx | C43: 8 | D43: 120 | E43: Faturada | F43: 5405 | H43: 100 | I43: VENDAS A CONSUMIDOR | J43: PORTO ALEGRE | K43: RS-Rio Grande do Sul | L43: 46029 | M43: 25.55 | O43: 242272 | P43: NFC-e enviada | Q43: Cód: 0 | U43: 1-Rodoviário | Z43: PATRICIA | AB43: =VALUE(SUBSTITUTE(BASE_5_2_3_B[[#This Row],[Pedido]],"Cód: ","")) -> 0
A44: SIGER_XLS_944116_260326_100411.xlsx | C44: 8 | D44: 121 | E44: Faturada | F44: 5102 | G44: 5405 | H44: 100 | I44: VENDAS A CONSUMIDOR | J44: PORTO ALEGRE | K44: RS-Rio Grande do Sul | L44: 46029 | M44: 138.23 | O44: 242282 | P44: NFC-e enviada | Q44: Cód: 0 | U44: 1-Rodoviário | Z44: PATRICIA | AB44: =VALUE(SUBSTITUTE(BASE_5_2_3_B[[#This Row],[Pedido]],"Cód: ","")) -> 0
A45: SIGER_XLS_944116_260326_100411.xlsx | C45: 8 | D45: 122 | E45: Faturada | F45: 5102 | G45: 5405 | H45: 100 | I45: VENDAS A CONSUMIDOR | J45: PORTO ALEGRE | K45: RS-Rio Grande do Sul | L45: 46029 | M45: 175.66 | O45: 242295 | P45: NFC-e enviada | Q45: Cód: 0 | U45: 1-Rodoviário | Z45: PATRICIA | AB45: =VALUE(SUBSTITUTE(BASE_5_2_3_B[[#This Row],[Pedido]],"Cód: ","")) -> 0
A46: SIGER_XLS_944116_260326_100411.xlsx | C46: 8 | D46: 123 | E46: Faturada | F46: 5405 | H46: 100 | I46: VENDAS A CONSUMIDOR | J46: PORTO ALEGRE | K46: RS-Rio Grande do Sul | L46: 46029 | M46: 86.48 | O46: 242306 | P46: NFC-e enviada | Q46: Cód: 0 | U46: 1-Rodoviário | Z46: PATRICIA | AB46: =VALUE(SUBSTITUTE(BASE_5_2_3_B[[#This Row],[Pedido]],"Cód: ","")) -> 0
A47: SIGER_XLS_944116_260326_100411.xlsx | C47: 8 | D47: 124 | E47: Faturada | F47: 5405 | H47: 13903 | I47: JULIO CESAR | J47: PORTO ALEGRE | K47: RS-Rio Grande do Sul | L47: 46029 | M47: 16.11 | O47: 242329 | P47: NFC-e enviada | Q47: Cód: 0 | U47: 1-Rodoviário | Z47: PATRICIA | AB47: =VALUE(SUBSTITUTE(BASE_5_2_3_B[[#This Row],[Pedido]],"Cód: ","")) -> 0
A48: SIGER_XLS_944116_260326_100411.xlsx | C48: 8 | D48: 125 | E48: Faturada | F48: 5405 | H48: 100 | I48: VENDAS A CONSUMIDOR | J48: PORTO ALEGRE | K48: RS-Rio Grande do Sul | L48: 46029 | M48: 5 | O48: 242343 | P48: NFC-e enviada | Q48: Cód: 0 | U48: 1-Rodoviário | Z48: PATRICIA | AB48: =VALUE(SUBSTITUTE(BASE_5_2_3_B[[#This Row],[Pedido]],"Cód: ","")) -> 0
A49: SIGER_XLS_944116_260326_100411.xlsx | C49: 8 | D49: 126 | E49: Faturada | F49: 5405 | H49: 100 | I49: VENDAS A CONSUMIDOR | J49: PORTO ALEGRE | K49: RS-Rio Grande do Sul | L49: 46029 | M49: 53.35 | O49: 242352 | P49: NFC-e enviada | Q49: Cód: 0 | U49: 1-Rodoviário | Z49: PATRICIA | AB49: =VALUE(SUBSTITUTE(BASE_5_2_3_B[[#This Row],[Pedido]],"Cód: ","")) -> 0
A50: SIGER_XLS_944116_260326_100411.xlsx | C50: 8 | D50: 127 | E50: Faturada | F50: 5102 | G50: 5405 | H50: 100 | I50: VENDAS A CONSUMIDOR | J50: PORTO ALEGRE | K50: RS-Rio Grande do Sul | L50: 46029 | M50: 293.34 | O50: 242353 | P50: NFC-e enviada | Q50: Cód: 0 | U50: 1-Rodoviário | Z50: PATRICIA | AB50: =VALUE(SUBSTITUTE(BASE_5_2_3_B[[#This Row],[Pedido]],"Cód: ","")) -> 0
A51: SIGER_XLS_944116_260326_100411.xlsx | C51: 8 | D51: 128 | E51: Faturada | F51: 5102 | G51: 5405 | H51: 100 | I51: VENDAS A CONSUMIDOR | J51: PORTO ALEGRE | K51: RS-Rio Grande do Sul | L51: 46030 | M51: 68.3 | O51: 242360 | P51: NFC-e enviada | Q51: Cód: 0 | U51: 1-Rodoviário | Z51: PATRICIA | AB51: =VALUE(SUBSTITUTE(BASE_5_2_3_B[[#This Row],[Pedido]],"Cód: ","")) -> 0
A52: SIGER_XLS_944116_260326_100411.xlsx | C52: 8 | D52: 129 | E52: Faturada | F52: 5102 | G52: 5405 | H52: 100 | I52: VENDAS A CONSUMIDOR | J52: PORTO ALEGRE | K52: RS-Rio Grande do Sul | L52: 46030 | M52: 47.92 | O52: 242363 | P52: NFC-e enviada | Q52: Cód: 0 | U52: 1-Rodoviário | Z52: PATRICIA | AB52: =VALUE(SUBSTITUTE(BASE_5_2_3_B[[#This Row],[Pedido]],"Cód: ","")) -> 0
A53: SIGER_XLS_944116_260326_100411.xlsx | C53: 8 | D53: 130 | E53: Faturada | F53: 5102 | G53: 5405 | H53: 100 | I53: VENDAS A CONSUMIDOR | J53: PORTO ALEGRE | K53: RS-Rio Grande do Sul | L53: 46030 | M53: 82.35 | O53: 242385 | P53: NFC-e enviada | Q53: Cód: 0 | U53: 1-Rodoviário | Z53: PATRICIA | AB53: =VALUE(SUBSTITUTE(BASE_5_2_3_B[[#This Row],[Pedido]],"Cód: ","")) -> 0
A54: SIGER_XLS_944116_260326_100411.xlsx | C54: 8 | D54: 131 | E54: Faturada | F54: 5405 | H54: 100 | I54: VENDAS A CONSUMIDOR | J54: PORTO ALEGRE | K54: RS-Rio Grande do Sul | L54: 46030 | M54: 146.32 | O54: 242388 | P54: NFC-e enviada | Q54: Cód: 0 | U54: 1-Rodoviário | Z54: PATRICIA | AB54: =VALUE(SUBSTITUTE(BASE_5_2_3_B[[#This Row],[Pedido]],"Cód: ","")) -> 0
A55: SIGER_XLS_944116_260326_100411.xlsx | C55: 8 | D55: 132 | E55: Faturada | F55: 5405 | H55: 100 | I55: VENDAS A CONSUMIDOR | J55: PORTO ALEGRE | K55: RS-Rio Grande do Sul | L55: 46030 | M55: 8.46 | O55: 242412 | P55: NFC-e enviada | Q55: Cód: 0 | U55: 1-Rodoviário | Z55: PATRICIA | AB55: =VALUE(SUBSTITUTE(BASE_5_2_3_B[[#This Row],[Pedido]],"Cód: ","")) -> 0
A56: SIGER_XLS_944116_260326_100411.xlsx | C56: 8 | D56: 133 | E56: Faturada | F56: 5405 | H56: 100 | I56: VENDAS A CONSUMIDOR | J56: PORTO ALEGRE | K56: RS-Rio Grande do Sul | L56: 46030 | M56: 31.48 | O56: 242422 | P56: NFC-e enviada | Q56: Cód: 0 | U56: 1-Rodoviário | Z56: RAEL | AB56: =VALUE(SUBSTITUTE(BASE_5_2_3_B[[#This Row],[Pedido]],"Cód: ","")) -> 0
A57: SIGER_XLS_944116_260326_100411.xlsx | C57: 8 | D57: 134 | E57: Faturada | F57: 5405 | H57: 100 | I57: VENDAS A CONSUMIDOR | J57: PORTO ALEGRE | K57: RS-Rio Grande do Sul | L57: 46030 | M57: 46.65 | O57: 242426 | P57: NFC-e enviada | Q57: Cód: 0 | U57: 1-Rodoviário | Z57: PATRICIA | AB57: =VALUE(SUBSTITUTE(BASE_5_2_3_B[[#This Row],[Pedido]],"Cód: ","")) -> 0
A58: SIGER_XLS_944116_260326_100411.xlsx | C58: 8 | D58: 135 | E58: Faturada | F58: 5102 | G58: 5405 | H58: 100 | I58: VENDAS A CONSUMIDOR | J58: PORTO ALEGRE | K58: RS-Rio Grande do Sul | L58: 46030 | M58: 62.58 | O58: 242454 | P58: NFC-e enviada | Q58: Cód: 0 | U58: 1-Rodoviário | Z58: PATRICIA | AB58: =VALUE(SUBSTITUTE(BASE_5_2_3_B[[#This Row],[Pedido]],"Cód: ","")) -> 0
A59: SIGER_XLS_944116_260326_100411.xlsx | C59: 8 | D59: 136 | E59: Faturada | F59: 5102 | G59: 5405 | H59: 100 | I59: VENDAS A CONSUMIDOR | J59: PORTO ALEGRE | K59: RS-Rio Grande do Sul | L59: 46030 | M59: 169.23 | O59: 242465 | P59: NFC-e enviada | Q59: Cód: 0 | U59: 1-Rodoviário | Z59: PATRICIA | AB59: =VALUE(SUBSTITUTE(BASE_5_2_3_B[[#This Row],[Pedido]],"Cód: ","")) -> 0
A60: SIGER_XLS_944116_260326_100411.xlsx | C60: 8 | D60: 137 | E60: Faturada | F60: 5102 | G60: 5405 | H60: 100 | I60: VENDAS A CONSUMIDOR | J60: PORTO ALEGRE | K60: RS-Rio Grande do Sul | L60: 46030 | M60: 83.32 | O60: 242468 | P60: NFC-e enviada | Q60: Cód: 0 | U60: 1-Rodoviário | Z60: PATRICIA | AB60: =VALUE(SUBSTITUTE(BASE_5_2_3_B[[#This Row],[Pedido]],"Cód: ","")) -> 0
A61: SIGER_XLS_944116_260326_100411.xlsx | C61: 8 | D61: 138 | E61: Faturada | F61: 5102 | G61: 5405 | H61: 100 | I61: VENDAS A CONSUMIDOR | J61: PORTO ALEGRE | K61: RS-Rio Grande do Sul | L61: 46030 | M61: 78.19 | O61: 242471 | P61: NFC-e enviada | Q61: Cód: 0 | U61: 1-Rodoviário | Z61: PATRICIA | AB61: =VALUE(SUBSTITUTE(BASE_5_2_3_B[[#This Row],[Pedido]],"Cód: ","")) -> 0
A62: SIGER_XLS_944116_260326_100411.xlsx | C62: 8 | D62: 139 | E62: Faturada | F62: 5102 | G62: 5405 | H62: 100 | I62: VENDAS A CONSUMIDOR | J62: PORTO ALEGRE | K62: RS-Rio Grande do Sul | L62: 46030 | M62: 40.26 | O62: 242495 | P62: NFC-e enviada | Q62: Cód: 0 | U62: 1-Rodoviário | Z62: PATRICIA | AB62: =VALUE(SUBSTITUTE(BASE_5_2_3_B[[#This Row],[Pedido]],"Cód: ","")) -> 0
A63: SIGER_XLS_944116_260326_100411.xlsx | C63: 8 | D63: 140 | E63: Faturada | F63: 5102 | G63: 5405 | H63: 100 | I63: VENDAS A CONSUMIDOR | J63: PORTO ALEGRE | K63: RS-Rio Grande do Sul | L63: 46030 | M63: 24.17 | O63: 242518 | P63: NFC-e enviada | Q63: Cód: 0 | U63: 1-Rodoviário | Z63: PATRICIA | AB63: =VALUE(SUBSTITUTE(BASE_5_2_3_B[[#This Row],[Pedido]],"Cód: ","")) -> 0
A64: SIGER_XLS_944116_260326_100411.xlsx | C64: 8 | D64: 141 | E64: Faturada | F64: 5102 | G64: 5405 | H64: 100 | I64: VENDAS A CONSUMIDOR | J64: PORTO ALEGRE | K64: RS-Rio Grande do Sul | L64: 46030 | M64: 138.52 | O64: 242532 | P64: NFC-e enviada | Q64: Cód: 0 | U64: 1-Rodoviário | Z64: PATRICIA | AB64: =VALUE(SUBSTITUTE(BASE_5_2_3_B[[#This Row],[Pedido]],"Cód: ","")) -> 0
A65: SIGER_XLS_944116_260326_100411.xlsx | C65: 8 | D65: 142 | E65: Faturada | F65: 5102 | G65: 5405 | H65: 100 | I65: VENDAS A CONSUMIDOR | J65: PORTO ALEGRE | K65: RS-Rio Grande do Sul | L65: 46031 | M65: 101.12 | O65: 242547 | P65: NFC-e enviada | Q65: Cód: 0 | U65: 1-Rodoviário | Z65: PATRICIA | AB65: =VALUE(SUBSTITUTE(BASE_5_2_3_B[[#This Row],[Pedido]],"Cód: ","")) -> 0
A66: SIGER_XLS_944116_260326_100411.xlsx | C66: 8 | D66: 143 | E66: Faturada | F66: 5405 | H66: 100 | I66: VENDAS A CONSUMIDOR | J66: PORTO ALEGRE | K66: RS-Rio Grande do Sul | L66: 46031 | M66: 52.44 | O66: 242557 | P66: NFC-e enviada | Q66: Cód: 0 | U66: 1-Rodoviário | Z66: PATRICIA | AB66: =VALUE(SUBSTITUTE(BASE_5_2_3_B[[#This Row],[Pedido]],"Cód: ","")) -> 0
A67: SIGER_XLS_944116_260326_100411.xlsx | C67: 8 | D67: 144 | E67: Faturada | F67: 5102 | G67: 5405 | H67: 100 | I67: VENDAS A CONSUMIDOR | J67: PORTO ALEGRE | K67: RS-Rio Grande do Sul | L67: 46031 | M67: 20.96 | O67: 242577 | P67: NFC-e enviada | Q67: Cód: 0 | U67: 1-Rodoviário | Z67: PATRICIA | AB67: =VALUE(SUBSTITUTE(BASE_5_2_3_B[[#This Row],[Pedido]],"Cód: ","")) -> 0
A68: SIGER_XLS_944116_260326_100411.xlsx | C68: 8 | D68: 145 | E68: Faturada | F68: 5405 | H68: 100 | I68: VENDAS A CONSUMIDOR | J68: PORTO ALEGRE | K68: RS-Rio Grande do Sul | L68: 46031 | M68: 23.55 | O68: 242584 | P68: NFC-e enviada | Q68: Cód: 0 | U68: 1-Rodoviário | Z68: PATRICIA | AB68: =VALUE(SUBSTITUTE(BASE_5_2_3_B[[#This Row],[Pedido]],"Cód: ","")) -> 0
A69: SIGER_XLS_944116_260326_100411.xlsx | C69: 8 | D69: 146 | E69: Faturada | F69: 5405 | H69: 100 | I69: VENDAS A CONSUMIDOR | J69: PORTO ALEGRE | K69: RS-Rio Grande do Sul | L69: 46031 | M69: 5 | O69: 242589 | P69: NFC-e enviada | Q69: Cód: 0 | U69: 1-Rodoviário | Z69: PATRICIA | AB69: =VALUE(SUBSTITUTE(BASE_5_2_3_B[[#This Row],[Pedido]],"Cód: ","")) -> 0
A70: SIGER_XLS_944116_260326_100411.xlsx | C70: 8 | D70: 147 | E70: Faturada | F70: 5102 | G70: 5405 | H70: 100 | I70: VENDAS A CONSUMIDOR | J70: PORTO ALEGRE | K70: RS-Rio Grande do Sul | L70: 46031 | M70: 22.16 | O70: 242600 | P70: NFC-e enviada | Q70: Cód: 0 | U70: 1-Rodoviário | Z70: PATRICIA | AB70: =VALUE(SUBSTITUTE(BASE_5_2_3_B[[#This Row],[Pedido]],"Cód: ","")) -> 0
A71: SIGER_XLS_944116_260326_100411.xlsx | C71: 8 | D71: 148 | E71: Faturada | F71: 5405 | H71: 100 | I71: VENDAS A CONSUMIDOR | J71: PORTO ALEGRE | K71: RS-Rio Grande do Sul | L71: 46031 | M71: 46.22 | O71: 242604 | P71: NFC-e enviada | Q71: Cód: 0 | U71: 1-Rodoviário | Z71: PATRICIA | AB71: =VALUE(SUBSTITUTE(BASE_5_2_3_B[[#This Row],[Pedido]],"Cód: ","")) -> 0
A72: SIGER_XLS_944116_260326_100411.xlsx | C72: 8 | D72: 149 | E72: Faturada | F72: 5102 | G72: 5405 | H72: 100 | I72: VENDAS A CONSUMIDOR | J72: PORTO ALEGRE | K72: RS-Rio Grande do Sul | L72: 46031 | M72: 99.6 | O72: 242615 | P72: NFC-e enviada | Q72: Cód: 0 | U72: 1-Rodoviário | Z72: RAEL | AB72: =VALUE(SUBSTITUTE(BASE_5_2_3_B[[#This Row],[Pedido]],"Cód: ","")) -> 0
A73: SIGER_XLS_944116_260326_100411.xlsx | C73: 8 | D73: 150 | E73: Faturada | F73: 5102 | G73: 5405 | H73: 100 | I73: VENDAS A CONSUMIDOR | J73: PORTO ALEGRE | K73: RS-Rio Grande do Sul | L73: 46031 | M73: 6.95 | O73: 242617 | P73: NFC-e enviada | Q73: Cód: 0 | U73: 1-Rodoviário | Z73: RAEL | AB73: =VALUE(SUBSTITUTE(BASE_5_2_3_B[[#This Row],[Pedido]],"Cód: ","")) -> 0
A74: SIGER_XLS_944116_260326_100411.xlsx | C74: 8 | D74: 151 | E74: Faturada | F74: 5405 | H74: 14047 | I74: RODOLFO | J74: PORTO ALEGRE | K74: RS-Rio Grande do Sul | L74: 46031 | M74: 7.33 | O74: 242624 | P74: NFC-e enviada | Q74: Cód: 0 | U74: 1-Rodoviário | Z74: ALEX | AB74: =VALUE(SUBSTITUTE(BASE_5_2_3_B[[#This Row],[Pedido]],"Cód: ","")) -> 0
A75: SIGER_XLS_944116_260326_100411.xlsx | C75: 8 | D75: 152 | E75: Faturada | F75: 5405 | H75: 100 | I75: VENDAS A CONSUMIDOR | J75: PORTO ALEGRE | K75: RS-Rio Grande do Sul | L75: 46031 | M75: 24.17 | O75: 242653 | P75: NFC-e enviada | Q75: Cód: 0 | U75: 1-Rodoviário | Z75: PATRICIA | AB75: =VALUE(SUBSTITUTE(BASE_5_2_3_B[[#This Row],[Pedido]],"Cód: ","")) -> 0
A76: SIGER_XLS_944116_260326_100411.xlsx | C76: 8 | D76: 153 | E76: Faturada | F76: 5405 | H76: 100 | I76: VENDAS A CONSUMIDOR | J76: PORTO ALEGRE | K76: RS-Rio Grande do Sul | L76: 46031 | M76: 6.51 | O76: 242669 | P76: NFC-e enviada | Q76: Cód: 0 | U76: 1-Rodoviário | Z76: PATRICIA | AB76: =VALUE(SUBSTITUTE(BASE_5_2_3_B[[#This Row],[Pedido]],"Cód: ","")) -> 0
A77: SIGER_XLS_944116_260326_100411.xlsx | C77: 8 | D77: 154 | E77: Faturada | F77: 5405 | H77: 100 | I77: VENDAS A CONSUMIDOR | J77: PORTO ALEGRE | K77: RS-Rio Grande do Sul | L77: 46031 | M77: 21.37 | O77: 242674 | P77: NFC-e enviada | Q77: Cód: 0 | U77: 1-Rodoviário | Z77: PATRICIA | AB77: =VALUE(SUBSTITUTE(BASE_5_2_3_B[[#This Row],[Pedido]],"Cód: ","")) -> 0
A78: SIGER_XLS_944116_260326_100411.xlsx | C78: 8 | D78: 155 | E78: Faturada | F78: 5102 | G78: 5405 | H78: 100 | I78: VENDAS A CONSUMIDOR | J78: PORTO ALEGRE | K78: RS-Rio Grande do Sul | L78: 46031 | M78: 51.45 | O78: 242690 | P78: NFC-e enviada | Q78: Cód: 0 | U78: 1-Rodoviário | Z78: PATRICIA | AB78: =VALUE(SUBSTITUTE(BASE_5_2_3_B[[#This Row],[Pedido]],"Cód: ","")) -> 0
A79: SIGER_XLS_944116_260326_100411.xlsx | C79: 8 | D79: 156 | E79: Faturada | F79: 5405 | H79: 100 | I79: VENDAS A CONSUMIDOR | J79: PORTO ALEGRE | K79: RS-Rio Grande do Sul | L79: 46031 | M79: 6.72 | O79: 242715 | P79: NFC-e enviada | Q79: Cód: 0 | U79: 1-Rodoviário | Z79: PATRICIA | AB79: =VALUE(SUBSTITUTE(BASE_5_2_3_B[[#This Row],[Pedido]],"Cód: ","")) -> 0
A80: SIGER_XLS_944116_260326_100411.xlsx | C80: 8 | D80: 157 | E80: Faturada | F80: 5102 | G80: 5405 | H80: 100 | I80: VENDAS A CONSUMIDOR | J80: PORTO ALEGRE | K80: RS-Rio Grande do Sul | L80: 46034 | M80: 88.14 | O80: 242739 | P80: NFC-e enviada | Q80: Cód: 0 | U80: 1-Rodoviário | Z80: PATRICIA | AB80: =VALUE(SUBSTITUTE(BASE_5_2_3_B[[#This Row],[Pedido]],"Cód: ","")) -> 0
A81: SIGER_XLS_944116_260326_100411.xlsx | C81: 8 | D81: 158 | E81: Faturada | F81: 5405 | H81: 100 | I81: VENDAS A CONSUMIDOR | J81: PORTO ALEGRE | K81: RS-Rio Grande do Sul | L81: 46034 | M81: 12.54 | O81: 242743 | P81: NFC-e enviada | Q81: Cód: 0 | U81: 1-Rodoviário | Z81: PATRICIA | AB81: =VALUE(SUBSTITUTE(BASE_5_2_3_B[[#This Row],[Pedido]],"Cód: ","")) -> 0
A82: SIGER_XLS_944116_260326_100411.xlsx | C82: 8 | D82: 159 | E82: Faturada | F82: 5405 | H82: 100 | I82: VENDAS A CONSUMIDOR | J82: PORTO ALEGRE | K82: RS-Rio Grande do Sul | L82: 46034 | M82: 37.26 | O82: 242753 | P82: NFC-e enviada | Q82: Cód: 0 | U82: 1-Rodoviário | Z82: PATRICIA | AB82: =VALUE(SUBSTITUTE(BASE_5_2_3_B[[#This Row],[Pedido]],"Cód: ","")) -> 0
A83: SIGER_XLS_944116_260326_100411.xlsx | C83: 8 | D83: 160 | E83: Faturada | F83: 5405 | H83: 100 | I83: VENDAS A CONSUMIDOR | J83: PORTO ALEGRE | K83: RS-Rio Grande do Sul | L83: 46034 | M83: 6.42 | O83: 242759 | P83: NFC-e enviada | Q83: Cód: 0 | U83: 1-Rodoviário | Z83: PATRICIA | AB83: =VALUE(SUBSTITUTE(BASE_5_2_3_B[[#This Row],[Pedido]],"Cód: ","")) -> 0
A84: SIGER_XLS_944116_260326_100411.xlsx | C84: 8 | D84: 161 | E84: Faturada | F84: 5405 | H84: 100 | I84: VENDAS A CONSUMIDOR | J84: PORTO ALEGRE | K84: RS-Rio Grande do Sul | L84: 46034 | M84: 5 | O84: 242761 | P84: NFC-e enviada | Q84: Cód: 0 | U84: 1-Rodoviário | Z84: PATRICIA | AB84: =VALUE(SUBSTITUTE(BASE_5_2_3_B[[#This Row],[Pedido]],"Cód: ","")) -> 0
A85: SIGER_XLS_944116_260326_100411.xlsx | C85: 8 | D85: 162 | E85: Faturada | F85: 5405 | H85: 100 | I85: VENDAS A CONSUMIDOR | J85: PORTO ALEGRE | K85: RS-Rio Grande do Sul | L85: 46034 | M85: 26.67 | O85: 242806 | P85: NFC-e enviada | Q85: Cód: 0 | U85: 1-Rodoviário | Z85: PATRICIA | AB85: =VALUE(SUBSTITUTE(BASE_5_2_3_B[[#This Row],[Pedido]],"Cód: ","")) -> 0
A86: SIGER_XLS_944116_260326_100411.xlsx | C86: 8 | D86: 163 | E86: Faturada | F86: 5405 | H86: 100 | I86: VENDAS A CONSUMIDOR | J86: PORTO ALEGRE | K86: RS-Rio Grande do Sul | L86: 46034 | M86: 52.24 | O86: 242808 | P86: NFC-e enviada | Q86: Cód: 0 | U86: 1-Rodoviário | Z86: RAEL | AB86: =VALUE(SUBSTITUTE(BASE_5_2_3_B[[#This Row],[Pedido]],"Cód: ","")) -> 0
A87: SIGER_XLS_944116_260326_100411.xlsx | C87: 8 | D87: 164 | E87: Faturada | F87: 5405 | H87: 100 | I87: VENDAS A CONSUMIDOR | J87: PORTO ALEGRE | K87: RS-Rio Grande do Sul | L87: 46034 | M87: 274.03 | O87: 242810 | P87: NFC-e enviada | Q87: Cód: 0 | U87: 1-Rodoviário | Z87: RAEL | AB87: =VALUE(SUBSTITUTE(BASE_5_2_3_B[[#This Row],[Pedido]],"Cód: ","")) -> 0
A88: SIGER_XLS_944116_260326_100411.xlsx | C88: 8 | D88: 165 | E88: Faturada | F88: 5102 | G88: 5405 | H88: 100 | I88: VENDAS A CONSUMIDOR | J88: PORTO ALEGRE | K88: RS-Rio Grande do Sul | L88: 46034 | M88: 75 | O88: 242811 | P88: NFC-e enviada | Q88: Cód: 0 | U88: 1-Rodoviário | Z88: RAEL | AB88: =VALUE(SUBSTITUTE(BASE_5_2_3_B[[#This Row],[Pedido]],"Cód: ","")) -> 0
A89: SIGER_XLS_944116_260326_100411.xlsx | C89: 8 | D89: 166 | E89: Faturada | F89: 5405 | H89: 100 | I89: VENDAS A CONSUMIDOR | J89: PORTO ALEGRE | K89: RS-Rio Grande do Sul | L89: 46034 | M89: 87.83 | O89: 242831 | P89: NFC-e enviada | Q89: Cód: 0 | U89: 1-Rodoviário | Z89: PATRICIA | AB89: =VALUE(SUBSTITUTE(BASE_5_2_3_B[[#This Row],[Pedido]],"Cód: ","")) -> 0
A90: SIGER_XLS_944116_260326_100411.xlsx | C90: 8 | D90: 167 | E90: Faturada | F90: 5405 | H90: 100 | I90: VENDAS A CONSUMIDOR | J90: PORTO ALEGRE | K90: RS-Rio Grande do Sul | L90: 46034 | M90: 35.19 | O90: 242851 | P90: NFC-e enviada | Q90: Cód: 0 | U90: 1-Rodoviário | Z90: PATRICIA | AB90: =VALUE(SUBSTITUTE(BASE_5_2_3_B[[#This Row],[Pedido]],"Cód: ","")) -> 0
A91: SIGER_XLS_944116_260326_100411.xlsx | C91: 8 | D91: 168 | E91: Faturada | F91: 5405 | H91: 100 | I91: VENDAS A CONSUMIDOR | J91: PORTO ALEGRE | K91: RS-Rio Grande do Sul | L91: 46034 | M91: 68.85 | O91: 242858 | P91: NFC-e enviada | Q91: Cód: 0 | U91: 1-Rodoviário | Z91: PATRICIA | AB91: =VALUE(SUBSTITUTE(BASE_5_2_3_B[[#This Row],[Pedido]],"Cód: ","")) -> 0
A92: SIGER_XLS_944116_260326_100411.xlsx | C92: 8 | D92: 169 | E92: Faturada | F92: 5405 | H92: 100 | I92: VENDAS A CONSUMIDOR | J92: PORTO ALEGRE | K92: RS-Rio Grande do Sul | L92: 46034 | M92: 87.98 | O92: 242864 | P92: NFC-e enviada | Q92: Cód: 0 | U92: 1-Rodoviário | Z92: PATRICIA | AB92: =VALUE(SUBSTITUTE(BASE_5_2_3_B[[#This Row],[Pedido]],"Cód: ","")) -> 0
A93: SIGER_XLS_944116_260326_100411.xlsx | C93: 8 | D93: 170 | E93: Faturada | F93: 5405 | H93: 100 | I93: VENDAS A CONSUMIDOR | J93: PORTO ALEGRE | K93: RS-Rio Grande do Sul | L93: 46034 | M93: 49.13 | O93: 242881 | P93: NFC-e enviada | Q93: Cód: 0 | U93: 1-Rodoviário | Z93: PATRICIA | AB93: =VALUE(SUBSTITUTE(BASE_5_2_3_B[[#This Row],[Pedido]],"Cód: ","")) -> 0
A94: SIGER_XLS_944116_260326_100411.xlsx | C94: 8 | D94: 171 | E94: Faturada | F94: 5405 | H94: 100 | I94: VENDAS A CONSUMIDOR | J94: PORTO ALEGRE | K94: RS-Rio Grande do Sul | L94: 46034 | M94: 5 | O94: 242889 | P94: NFC-e enviada | Q94: Cód: 0 | U94: 1-Rodoviário | Z94: PATRICIA | AB94: =VALUE(SUBSTITUTE(BASE_5_2_3_B[[#This Row],[Pedido]],"Cód: ","")) -> 0
A95: SIGER_XLS_944116_260326_100411.xlsx | C95: 8 | D95: 172 | E95: Faturada | F95: 5405 | H95: 100 | I95: VENDAS A CONSUMIDOR | J95: PORTO ALEGRE | K95: RS-Rio Grande do Sul | L95: 46035 | M95: 31.18 | O95: 242915 | P95: NFC-e enviada | Q95: Cód: 0 | U95: 1-Rodoviário | Z95: PATRICIA | AB95: =VALUE(SUBSTITUTE(BASE_5_2_3_B[[#This Row],[Pedido]],"Cód: ","")) -> 0
A96: SIGER_XLS_944116_260326_100411.xlsx | C96: 8 | D96: 173 | E96: Faturada | F96: 5405 | H96: 100 | I96: VENDAS A CONSUMIDOR | J96: PORTO ALEGRE | K96: RS-Rio Grande do Sul | L96: 46035 | M96: 88.64 | O96: 242932 | P96: NFC-e enviada | Q96: Cód: 0 | U96: 1-Rodoviário | Z96: PATRICIA | AB96: =VALUE(SUBSTITUTE(BASE_5_2_3_B[[#This Row],[Pedido]],"Cód: ","")) -> 0
A97: SIGER_XLS_944116_260326_100411.xlsx | C97: 8 | D97: 174 | E97: Faturada | F97: 5405 | H97: 100 | I97: VENDAS A CONSUMIDOR | J97: PORTO ALEGRE | K97: RS-Rio Grande do Sul | L97: 46035 | M97: 6.7 | O97: 242941 | P97: NFC-e enviada | Q97: Cód: 0 | U97: 1-Rodoviário | Z97: PATRICIA | AB97: =VALUE(SUBSTITUTE(BASE_5_2_3_B[[#This Row],[Pedido]],"Cód: ","")) -> 0
A98: SIGER_XLS_944116_260326_100411.xlsx | C98: 8 | D98: 175 | E98: Faturada | F98: 5102 | G98: 5405 | H98: 100 | I98: VENDAS A CONSUMIDOR | J98: PORTO ALEGRE | K98: RS-Rio Grande do Sul | L98: 46035 | M98: 78.02 | O98: 242947 | P98: NFC-e enviada | Q98: Cód: 0 | U98: 1-Rodoviário | Z98: PATRICIA | AB98: =VALUE(SUBSTITUTE(BASE_5_2_3_B[[#This Row],[Pedido]],"Cód: ","")) -> 0
A99: SIGER_XLS_944116_260326_100411.xlsx | C99: 8 | D99: 176 | E99: Faturada | F99: 5102 | G99: 5405 | H99: 100 | I99: VENDAS A CONSUMIDOR | J99: PORTO ALEGRE | K99: RS-Rio Grande do Sul | L99: 46035 | M99: 76.82 | O99: 242963 | P99: NFC-e enviada | Q99: Cód: 0 | U99: 1-Rodoviário | Z99: PATRICIA | AB99: =VALUE(SUBSTITUTE(BASE_5_2_3_B[[#This Row],[Pedido]],"Cód: ","")) -> 0
A100: SIGER_XLS_944116_260326_100411.xlsx | C100: 8 | D100: 177 | E100: Faturada | F100: 5405 | H100: 100 | I100: VENDAS A CONSUMIDOR | J100: PORTO ALEGRE | K100: RS-Rio Grande do Sul | L100: 46035 | M100: 61.41 | O100: 242968 | P100: NFC-e enviada | Q100: Cód: 0 | U100: 1-Rodoviário | Z100: PATRICIA | AB100: =VALUE(SUBSTITUTE(BASE_5_2_3_B[[#This Row],[Pedido]],"Cód: ","")) -> 0
...
